{
    "children": [
        {
            "id": "standard_4",
            "name": "Multiple categories",
            "children": [
                {
                    "id": "1_standard_4",
                    "name": "Second level",
                    "children": [
                        {
                            "id": "2_standard_4",
                            "name": "Fird level",
                            "children": [
                                {
                                    "id": "3_standard_4",
                                    "name": "Forth level",
                                    "children": [
                                        {
                                            "id": "4_standard_4",
                                            "name": "Fifth level",
                                            "children": [
                                                {
                                                    "id": "d86e9ac20cbe399a946b529395dd83c7a388c686",
                                                    "name": "User retrieval",
                                                    "description": "Within this route users get created",
                                                    "request": {
                                                        "url": "{{environment}}[\/:userId]",
                                                        "method": "PUT",
                                                        "needsAuthentication": false,
                                                        "params": [
                                                            {
                                                                "type": "uri",
                                                                "example": 12,
                                                                "data_type": "int",
                                                                "description": "The user's id",
                                                                "isOptional": false,
                                                                "name": "userId"
                                                            },
                                                            {
                                                                "type": "post",
                                                                "example": "Mark",
                                                                "data_type": "string",
                                                                "description": "The name of the user",
                                                                "isOptional": true,
                                                                "name": "name"
                                                            },
                                                            {
                                                                "type": "post",
                                                                "example": 23,
                                                                "data_type": "int",
                                                                "description": "User's age",
                                                                "isOptional": true,
                                                                "name": "age"
                                                            }
                                                        ]
                                                    },
                                                    "tags": [
                                                        "users",
                                                        "partial update"
                                                    ]
                                                }
                                            ]
                                        },
                                        {
                                            "id": "1059bfac6ad6b4b0155f9e4485aac127e8e5198f",
                                            "name": "User partial update",
                                            "description": "Within this route users get updated",
                                            "request": {
                                                "url": "{{environment}}[\/:userId]",
                                                "method": "PATCH",
                                                "needsAuthentication": false,
                                                "params": [
                                                    {
                                                        "type": "uri",
                                                        "example": 12,
                                                        "data_type": "int",
                                                        "description": "The user's id",
                                                        "isOptional": false,
                                                        "name": "userId"
                                                    },
                                                    {
                                                        "type": "post",
                                                        "example": "Mark",
                                                        "data_type": "string",
                                                        "description": "The name of the user",
                                                        "isOptional": true,
                                                        "name": "name"
                                                    },
                                                    {
                                                        "type": "post",
                                                        "example": 23,
                                                        "data_type": "int",
                                                        "description": "User's age",
                                                        "isOptional": true,
                                                        "name": "age"
                                                    }
                                                ]
                                            },
                                            "tags": [
                                                "users",
                                                "update"
                                            ]
                                        }
                                    ]
                                },
                                {
                                    "id": "ac0ad62a4c855027c5b92e3233c98c15f0bdf6cb",
                                    "name": "User retrieval",
                                    "description": "Within this route users get the user",
                                    "request": {
                                        "url": "{{environment}}[\/:userId]",
                                        "method": "GET",
                                        "needsAuthentication": false,
                                        "params": [
                                            {
                                                "type": "uri",
                                                "example": 23,
                                                "data_type": "int",
                                                "description": "User unique identifier",
                                                "isOptional": false,
                                                "name": "userId"
                                            }
                                        ]
                                    },
                                    "tags": [
                                        "users",
                                        "get"
                                    ]
                                }
                            ]
                        },
                        {
                            "id": "26848acdf35874948333afe67dc3c73472eded34",
                            "name": "User authentication",
                            "description": "Within this route users get the access token in order to call the api and retrieve information",
                            "request": {
                                "url": "{{environment}}\/oauth",
                                "method": "POST",
                                "needsAuthentication": false,
                                "params": [
                                    {
                                        "type": "post",
                                        "example": "test",
                                        "data_type": "string",
                                        "description": "Username of the current person",
                                        "isOptional": false,
                                        "name": "username"
                                    },
                                    {
                                        "type": "post",
                                        "example": "test",
                                        "data_type": "string",
                                        "description": "The users password",
                                        "isOptional": false,
                                        "name": "password"
                                    }
                                ]
                            },
                            "tags": [
                                "users",
                                "create"
                            ]
                        }
                    ]
                },
                {
                    "id": "5_standard_4",
                    "name": "Another level",
                    "children": [
                        {
                            "id": "ea1cf40a941704f625623d50c24abf9b471decc1",
                            "name": "User delete",
                            "description": "Within this route users get deleted",
                            "request": {
                                "url": "{{environment}}[\/:userId]",
                                "method": "DELETE",
                                "needsAuthentication": false,
                                "params": [
                                    {
                                        "type": "uri",
                                        "example": 23,
                                        "data_type": "int",
                                        "description": "User unique identifier",
                                        "isOptional": false,
                                        "name": "userId"
                                    }
                                ]
                            },
                            "tags": [
                                "users",
                                "delete"
                            ]
                        }
                    ]
                }
            ]
        }
    ]
}